django_datatables_serverside/__init__.py
django_datatables_serverside/_data_server.py
django_datatables_serverside/views.py
django_datatables_serverside-1.0.1.dist-info/licenses/LICENSE
django_datatables_serverside-1.0.1.dist-info/METADATA
django_datatables_serverside-1.0.1.dist-info/WHEEL
django_datatables_serverside-1.0.1.dist-info/top_level.txt
django_datatables_serverside-1.0.1.dist-info/RECORD
